yankee/__init__.py
yankee/base/__init__.py
yankee/base/accessor.py
yankee/base/deserializer.py
yankee/base/fields.py
yankee/base/fields_test.py
yankee/base/fixtures/__init__.py
yankee/base/fixtures/model.py
yankee/base/fixtures/nested/__init__.py
yankee/base/fixtures/nested/model/example.py
yankee/base/fixtures/nested/schema/example.py
yankee/base/fixtures/schema.py
yankee/base/schema.py
yankee/base/schema_test.py
yankee/codegen/__init__.py
yankee/codegen/dataclass_gen.py
yankee/codegen/dataclass_gen_test.py
yankee/codegen/example.py
yankee/data/__init__.py
yankee/data/attrdict.py
yankee/data/collection.py
yankee/data/collection_test.py
yankee/data/row.py
yankee/data/util.py
yankee/html/__init__.py
yankee/html/io/__init__.py
yankee/html/io/aps.py
yankee/html/io/aps_test.py
yankee/html/io/autodetect.py
yankee/html/io/autodetect_test.py
yankee/html/io/iterparse.py
yankee/html/io/iterparse_test.py
yankee/html/io/process.py
yankee/html/io/sample.py
yankee/html/schema/__init__.py
yankee/html/schema/accessor.py
yankee/html/schema/fields.py
yankee/html/schema/mixin.py
yankee/html/schema/schema.py
yankee/html/schema/test_schema.py
yankee/html/util.py
yankee/io/__init__.py
yankee/io/convert.py
yankee/io/iterparse.py
yankee/io/test/__init__.py
yankee/io/test/sample.txt
yankee/io/test/test_iterparse.py
yankee/json/__init__.py
yankee/json/schema/__init__.py
yankee/json/schema/accessor.py
yankee/json/schema/fields.py
yankee/json/schema/mixin.py
yankee/json/schema/schema.py
yankee/json/schema/test_schema.py
yankee/settings.py
yankee/util.py
yankee/version.py
yankee/xml/__init__.py
yankee/xml/fixtures/exchange-documents.xsd
yankee/xml/io/__init__.py
yankee/xml/io/aps.py
yankee/xml/io/aps_test.py
yankee/xml/io/autodetect.py
yankee/xml/io/autodetect_test.py
yankee/xml/io/iterparse.py
yankee/xml/io/iterparse_test.py
yankee/xml/io/process.py
yankee/xml/io/sample.py
yankee/xml/schema/__init__.py
yankee/xml/schema/accessor.py
yankee/xml/schema/fields.py
yankee/xml/schema/mixin.py
yankee-0.1.46.dist-info/METADATA
yankee-0.1.46.dist-info/WHEEL
yankee-0.1.46.dist-info/RECORD
