Metadata-Version: 2.1
Name: yankee
Version: 0.1.46
Summary: lightweight, simple, and fast declarative XML and JSON data extraction
Home-page: https://github.com/parkerhancock/gelatin_extract
License: Apache Software License 2.0
Keywords: deserialization,xml,json,deserialize
Author: Parker Hancock
Author-email: 633163+parkerhancock@users.noreply.github.com
Requires-Python: >=3.9,<3.13
Classifier: Development Status :: 3 - Alpha
Classifier: License :: Other/Proprietary License
Classifier: Programming Language :: Python :: 3
Classifier: Programming Language :: Python :: 3.9
Classifier: Programming Language :: Python :: 3.10
Classifier: Programming Language :: Python :: 3.11
Classifier: Topic :: Text Processing :: Markup :: XML
Requires-Dist: cssselect (>=1.2.0,<2.0.0)
Requires-Dist: jsonpath-ng (>=1.6.1,<2.0.0)
Requires-Dist: lxml (>=5.2.2,<6.0.0)
Requires-Dist: python-dateutil (>=2.9.0.post0,<3.0.0)
Requires-Dist: toolz (>=0.12.1,<0.13.0)
Requires-Dist: ujson (>=5.10.0,<6.0.0)
Project-URL: Repository, https://github.com/parkerhancock/gelatin_extract
